histcmp/__init__.py
histcmp/checks.py
histcmp/cli.py
histcmp/compare.py
histcmp/config.py
histcmp/console.py
histcmp/github.py
histcmp/icons.py
histcmp/plot.py
histcmp/report.py
histcmp/root_helpers.py
histcmp/static/alpinejs.intersect.min.js
histcmp/static/alpinejs.min.js
histcmp/static/css/main.css
histcmp/static/css/bulma/bulma-rtl.css
histcmp/static/css/bulma/bulma-rtl.css.map
histcmp/static/css/bulma/bulma-rtl.min.css
histcmp/static/css/bulma/bulma.css
histcmp/static/css/bulma/bulma.css.map
histcmp/static/css/bulma/bulma.min.css
histcmp/templates/base.html.j2
histcmp/templates/main.html.j2
histcmp-0.8.1.dist-info/METADATA
histcmp-0.8.1.dist-info/WHEEL
histcmp-0.8.1.dist-info/entry_points.txt
histcmp-0.8.1.dist-info/RECORD
